[
null,
{"id":1,"battlerName":"","characterIndex":1,"characterName":"Nature","classId":1,"equips":[1,0,0,0,0],"faceIndex":0,"faceName":"Barsik","traits":[],"initialLevel":1,"maxLevel":9,"name":"Барсик","nickname":"Ловкач","note":"","profile":"самый обычный кот."},
{"id":2,"battlerName":"","characterIndex":6,"characterName":"cat_fluffy","classId":1,"equips":[1,0,0,0,0],"faceIndex":0,"faceName":"Mars","traits":[],"initialLevel":9,"maxLevel":9,"name":"Марс","nickname":"Умник","note":"","profile":"соседский кот."},
{"id":3,"battlerName":"","characterIndex":7,"characterName":"cat_recolor","classId":1,"equips":[1,0,0,0,0],"faceIndex":0,"faceName":"Iris","traits":[],"initialLevel":9,"maxLevel":9,"name":"Ириска","nickname":"Дикарка","note":"","profile":"игривая и непокорная."},
{"id":4,"battlerName":"","characterIndex":4,"characterName":"cat_fluffy","classId":1,"equips":[1,0,0,0,0],"faceIndex":0,"faceName":"Mursik","traits":[],"initialLevel":9,"maxLevel":9,"name":"Мурзик","nickname":"Бродяга","note":"","profile":"немного угрюмый, но надежный."},
{"id":5,"battlerName":"","characterIndex":4,"characterName":"cat_recolor","classId":1,"equips":[1,0,0,0,0],"faceIndex":0,"faceName":"Miki","traits":[],"initialLevel":9,"maxLevel":9,"name":"Мики","nickname":"Колдунья","note":"","profile":"кошачья колдунья. во всех жизнях."},
{"id":6,"battlerName":"","characterIndex":0,"characterName":"Dina_char","classId":2,"equips":[0,0,0,0,0],"faceIndex":0,"faceName":"Dina","traits":[],"initialLevel":1,"maxLevel":99,"name":"Дина","nickname":"","note":"","profile":""},
{"id":7,"battlerName":"","characterIndex":0,"characterName":"Doctor_char","classId":2,"equips":[0,0,0,0,0],"faceIndex":0,"faceName":"Doctor","traits":[],"initialLevel":1,"maxLevel":99,"name":"Доктор","nickname":"","note":"","profile":""},
{"id":8,"battlerName":"","characterIndex":0,"characterName":"Monster","classId":3,"equips":[0,0,0,0,0],"faceIndex":0,"faceName":"Ratking","traits":[],"initialLevel":9,"maxLevel":99,"name":"Крысиный Король","nickname":"","note":"","profile":""},
{"id":9,"battlerName":"","characterIndex":0,"characterName":"$BigMonster1","classId":3,"equips":[0,0,0,0,0],"faceIndex":0,"faceName":"Death","traits":[],"initialLevel":99,"maxLevel":99,"name":"Нечто","nickname":"","note":"","profile":""}
]